LICENSE
MANIFEST.in
README
README.rst
setup.py
version
ohmlr/__init__.py
ohmlr/ohmlr.py
ohmlr.egg-info/PKG-INFO
ohmlr.egg-info/SOURCES.txt
ohmlr.egg-info/dependency_links.txt
ohmlr.egg-info/top_level.txt