Metadata-Version: 1.1
Name: ohmlr
Version: 0.0.8
Summary: One-hot multinomial logisitc regression
Home-page: http://joepatmckenna.github.io/ohmlr
Author: Joseph P. McKenna
Author-email: joepatmckenna@gmail.com
License: MIT
Download-URL: https://pypi.org/project/ohmlr
Keywords: inference,statistics,machine learning
Platform: UNKNOWN
Classifier: Programming Language :: Python :: 3
Classifier: Operating System :: OS Independent
